ComeToLoseMoney/__init__.py
ComeToLoseMoney/utils.py
ComeToLoseMoney/CustomExceptions/__init__.py
ComeToLoseMoney/CustomExceptions/date.py
ComeToLoseMoney/line_notify/__init__.py
ComeToLoseMoney/line_notify/module.py
ComeToLoseMoney-2.3.dist-info/METADATA
ComeToLoseMoney-2.3.dist-info/WHEEL
ComeToLoseMoney-2.3.dist-info/top_level.txt
ComeToLoseMoney-2.3.dist-info/RECORD
